kwhmeter_utils/__init__.py
kwhmeter_utils/common.py
kwhmeter_utils/factura_pvpc.py
kwhmeter_utils/influxDB.py
kwhmeter_utils/data/kwhmeter_influxDB_config.yml
kwhmeter_utils/data/kwhmeter_pvpc_config.yml
kwhmeter_utils/scripts/__init__.py
kwhmeter_utils/scripts/cli.py
kwhmeter_utils-0.1.5.dist-info/LICENSE
kwhmeter_utils-0.1.5.dist-info/METADATA
kwhmeter_utils-0.1.5.dist-info/WHEEL
kwhmeter_utils-0.1.5.dist-info/entry_points.txt
kwhmeter_utils-0.1.5.dist-info/top_level.txt
kwhmeter_utils-0.1.5.dist-info/RECORD
