Metadata-Version: 2.1
Name: kwhmeter_utils
Version: 0.1.5
Summary: Simulador de facturas PVPC
Home-page: https://github.com/nachoplus/kwhmeter_utils
Author: nachomas
Author-email: mas.ignacio@gmail.com
Classifier: Programming Language :: Python :: 3
Classifier: License :: OSI Approved :: MIT License
Classifier: Operating System :: OS Independent
Requires-Python: >=3.6
License-File: LICENSE
Requires-Dist: kwhmeter
Requires-Dist: pandas
Requires-Dist: influxdb
